gitw/__init__.py
gitw/__main__.py
gitw/py.typed
gitw/files/git
gitw/files/git.exe
gitw-0.0.1.dist-info/LICENSE
gitw-0.0.1.dist-info/METADATA
gitw-0.0.1.dist-info/WHEEL
gitw-0.0.1.dist-info/top_level.txt
gitw-0.0.1.dist-info/RECORD
