Metadata-Version: 2.1
Name: gitw
Version: 0.0.1
Summary: gitw
Author: fieryhenry
License: GNU General Public License v3 or later (GPLv3+)
Project-URL: Homepage, https://github.com/fieryhenry/gitw
Project-URL: Repository, https://github.com/fieryhenry/gitw
Project-URL: Issues, https://github.com/fieryhenry/gitw/issues
Project-URL: Changelog, https://github.com/fieryhenry/gitw/blob/master/CHANGELOG.md
Classifier: Development Status :: 3 - Alpha
Classifier: Intended Audience :: Developers
Classifier: Topic :: Software Development :: Version Control :: Git
Classifier: Programming Language :: Python :: 3
Classifier: Programming Language :: Python :: 3.9
Classifier: License :: OSI Approved :: GNU General Public License v3 or later (GPLv3+)
Classifier: Operating System :: OS Independent
Requires-Python: >=3.9
License-File: LICENSE
